openaoe/__init__.py
openaoe/main.py
openaoe/backend/__init__.py
openaoe/backend/api/__init__.py
openaoe/backend/api/route_claude.py
openaoe/backend/api/route_google.py
openaoe/backend/api/route_internlm.py
openaoe/backend/api/route_minimax.py
openaoe/backend/api/route_mistral.py
openaoe/backend/api/route_openai.py
openaoe/backend/api/route_xunfei.py
openaoe/backend/config/__init__.py
openaoe/backend/config/biz_config.py
openaoe/backend/config/constant.py
openaoe/backend/model/__init__.py
openaoe/backend/model/aoe_response.py
openaoe/backend/model/claude.py
openaoe/backend/model/google.py
openaoe/backend/model/internlm.py
openaoe/backend/model/minimax.py
openaoe/backend/model/mistral.py
openaoe/backend/model/openai.py
openaoe/backend/model/openaoe.py
openaoe/backend/model/xunfei.py
openaoe/backend/service/__init__.py
openaoe/backend/service/base.py
openaoe/backend/service/mistral.py
openaoe/backend/service/service_claude.py
openaoe/backend/service/service_google.py
openaoe/backend/service/service_internlm.py
openaoe/backend/service/service_minimax.py
openaoe/backend/service/service_openai.py
openaoe/backend/service/service_xunfei.py
openaoe/backend/util/__init__.py
openaoe/backend/util/convert.py
openaoe/backend/util/file.py
openaoe/backend/util/log.py
openaoe/backend/util/str_util.py
openaoe/backend/util/time_util.py
openaoe/frontend/dist/AOE_logo.svg
openaoe/frontend/dist/index.html
openaoe/frontend/dist/vite.svg
openaoe/frontend/dist/assets/A-017dd65e.svg
openaoe/frontend/dist/assets/AOE-b98456c3.svg
openaoe/frontend/dist/assets/KaTeX_AMS-Regular-0cdd387c.woff2
openaoe/frontend/dist/assets/KaTeX_AMS-Regular-30da91e8.woff
openaoe/frontend/dist/assets/KaTeX_AMS-Regular-68534840.ttf
openaoe/frontend/dist/assets/KaTeX_Caligraphic-Bold-07d8e303.ttf
openaoe/frontend/dist/assets/KaTeX_Caligraphic-Bold-1ae6bd74.woff
openaoe/frontend/dist/assets/KaTeX_Caligraphic-Bold-de7701e4.woff2
openaoe/frontend/dist/assets/KaTeX_Caligraphic-Regular-3398dd02.woff
openaoe-0.0.6.dist-info/LICENSE.txt
openaoe-0.0.6.dist-info/METADATA
openaoe-0.0.6.dist-info/WHEEL
openaoe-0.0.6.dist-info/entry_points.txt
openaoe-0.0.6.dist-info/top_level.txt
openaoe-0.0.6.dist-info/RECORD
